macsploit/__init__.py
macsploit/msapi.py
Macs_api-0.0.4.dist-info/LICENSE
Macs_api-0.0.4.dist-info/METADATA
Macs_api-0.0.4.dist-info/WHEEL
Macs_api-0.0.4.dist-info/top_level.txt
Macs_api-0.0.4.dist-info/RECORD
