Metadata-Version: 2.1
Name: Macs-api
Version: 0.0.4
Summary: A small example package
Author-email: Frank Kostine <frankkostine@gmail.com>
Project-URL: Homepage, https://github.com/draxsoft/msapi
Project-URL: Issues, https://github.com/draxsoft/msapi/issues
Classifier: Programming Language :: Python :: 3
Classifier: License :: OSI Approved :: MIT License
Classifier: Operating System :: OS Independent
Requires-Python: >=3.6
License-File: LICENSE
